{
  "global": {
    "globalAccent": {
      "value": "#0085F7",
      "type": "color"
    },
    "sm": {
      "value": "200px",
      "type": "sizing"
    },
    "m": {
      "value": "{sm} * 2",
      "type": "sizing"
    }
  },
  "dark": {
    "background": {
      "value": "#35363A",
      "type": "color"
    },
    "background-second": {
      "value": "#1F2124",
      "type": "color"
    },
    "accent": {
      "value": "#51aaf7",
      "type": "color"
    },
    "text": {
      "value": "#b8d5f0",
      "type": "color"
    },
    "text-light": {
      "value": "#4d5763",
      "type": "color"
    }
  },
  "light": {
    "background": {
      "value": "#EFF2F6",
      "type": "color"
    },
    "background-second": {
      "value": "#FFFFFF",
      "type": "color"
    },
    "accent": {
      "value": "#0085F7",
      "type": "color",
      "description": "Цвет акцента"
    },
    "text": {
      "value": "#6D7C95",
      "type": "color"
    },
    "text-light": {
      "value": "#D4DBE5",
      "type": "color"
    }
  },
  "$themes": [],
  "$metadata": {
    "tokenSetOrder": [
      "global",
      "dark",
      "light"
    ]
  }
}